labrador/__init__.py
labrador/core/document/__init__.py
labrador/core/document/schema.py
labrador/core/document_loaders/__init__.py
labrador/core/document_loaders/base.py
labrador/core/embeddings/__init__.py
labrador/core/embeddings/base.py
labrador/core/text_splitters/utils.py
labrador/core/utils/pairwise.py
labrador/document_loaders/__init__.py
labrador/document_loaders/directory.py
labrador/document_loaders/docx.py
labrador/document_loaders/html.py
labrador/document_loaders/json.py
labrador/document_loaders/pdf.py
labrador/document_loaders/s3.py
labrador/document_loaders/watson_discovery.py
labrador/embeddings/__init__.py
labrador/embeddings/huggingface.py
labrador/embeddings/watsonx.py
labrador/evaluation/__init__.py
labrador/evaluation/knowledge_base_coverage.py
labrador/monitor/__init__.py
labrador/monitor/watsonx.py
labrador/retrievers/__init__.py
labrador/retrievers/watson_discovery.py
labrador/text_splitters/__init__.py
labrador/text_splitters/semantic.py
labrador/text_splitters/sentence.py
labrador/text_splitters/token.py
labrador/vector_stores/__init__.py
labrador/vector_stores/chroma.py
labrador/vector_stores/elasticsearch.py
labrador_ai-0.6.1.dist-info/LICENSE
labrador_ai-0.6.1.dist-info/METADATA
labrador_ai-0.6.1.dist-info/WHEEL
labrador_ai-0.6.1.dist-info/RECORD
