Metadata-Version: 2.1
Name: labrador-ai
Version: 0.6.1
Summary: Load any data in one line of code and connect with AI applications
Home-page: https://github.com/leonardofurnielis/labrador
License: MIT
Keywords: retrieval,RAG,index,data,LLM,AI,NLP
Author: Leonardo Furnielis
Author-email: leonardofurnielis@outlook.com
Requires-Python: >=3.10,<4.0
Classifier: License :: OSI Approved :: MIT License
Classifier: Operating System :: OS Independent
Classifier: Programming Language :: Python :: 3
Classifier: Programming Language :: Python :: 3.10
Classifier: Programming Language :: Python :: 3.11
Classifier: Programming Language :: Python :: 3.12
Classifier: Programming Language :: Python :: 3.13
Classifier: Topic :: Scientific/Engineering :: Artificial Intelligence
Classifier: Topic :: Software Development :: Libraries :: Application Frameworks
Classifier: Topic :: Software Development :: Libraries :: Python Modules
Requires-Dist: nltk (>=3.8.1,<4.0.0)
Requires-Dist: numpy (>=1.26.4,<2.0.0)
Requires-Dist: pydantic (>=2.7.1,<3.0.0)
Requires-Dist: sentence-transformers (>=2.7.0,<3.0.0)
Requires-Dist: tiktoken (>=0.7.0,<0.8.0)
Requires-Dist: torch (==2.1.0)
Project-URL: Documentation, https://leonardofurnielis.github.io/labrador
Project-URL: Repository, https://github.com/leonardofurnielis/labrador
